<?xml version = '1.0' encoding = 'UTF-8'?>
<DataTypesDesign class="oracle.dbtools.crest.model.design.datatypes.DataTypesDesign" name="DataTypes" id="E3C037B7-214B-1D12-79D8-859ECD6CA9D8" mainViewID="E900A970-563D-7356-5F9B-4C4622715BF8">
<createdBy>username</createdBy>
<createdTime>2022-04-22 08:11:58 UTC</createdTime>
<ownerDesignName>wc_logical</ownerDesignName>
<shouldBeOpen>false</shouldBeOpen>
<collectionOfRefsPrefix>array_ref_</collectionOfRefsPrefix>
<collectionPrefix>array_</collectionPrefix>
<defaultArrayLimit>10</defaultArrayLimit>
<defaultCollectionType_Kind>ARRAY</defaultCollectionType_Kind>
<defaultCollectionType_Suffix>_Array</defaultCollectionType_Suffix>
<embeddedStructuredTypePrefix>inst_</embeddedStructuredTypePrefix>
<referencePrefix>ref_</referencePrefix>
<useRoleInAssociationEndAsName>true</useRoleInAssociationEndAsName>
</DataTypesDesign>
